pygryphon/__init__.py
pygryphon/greet.py
pygryphon-1.0.13.dist-info/LICENSE
pygryphon-1.0.13.dist-info/METADATA
pygryphon-1.0.13.dist-info/WHEEL
pygryphon-1.0.13.dist-info/top_level.txt
pygryphon-1.0.13.dist-info/RECORD
