Metadata-Version: 2.1
Name: pygryphon
Version: 1.0.13
Summary: A small package for wonderful servers
Author-email: alice <alice@wonderland.com>
Classifier: Programming Language :: Python :: 3
Classifier: Operating System :: OS Independent
Requires-Python: >=3.7
License-File: LICENSE
